darn_it/__init__.py
darn_it/darn_it.pypy311-pp73-arm-linux-gnu.so
darn_it-1.0.0.dist-info/METADATA
darn_it-1.0.0.dist-info/WHEEL
darn_it-1.0.0.dist-info/licenses/LICENSE
darn_it-1.0.0.dist-info/RECORD
