Metadata-Version: 2.4
Name: darn_it
Version: 1.0.0
Classifier: Programming Language :: Rust
Classifier: Programming Language :: Python :: Implementation :: CPython
Classifier: Programming Language :: Python :: Implementation :: PyPy
License-File: LICENSE
Summary: An opinionated chunker for markdown formatted text
Author-email: John C Ll Stokes <johnclstokes@hotmail.com>
Requires-Python: >=3.9
